<?xml version="1.0" encoding="utf-8" ?>
<dwsync>
<file name="variables-night.css" server="C:/xampp/htdocs/icems/" local="131648441848599318" remote="131648441840000000" Dst="0" />
<file name="variables-direction.css" server="C:/xampp/htdocs/icems/" local="131648441822250589" remote="131648441820000000" Dst="0" />
<file name="variables-time.css" server="C:/xampp/htdocs/icems/" local="131648441826263444" remote="131648441820000000" Dst="0" />
<file name="variables-moon.css" server="C:/xampp/htdocs/icems/" local="131648441832017538" remote="131648441830000000" Dst="0" />
<file name="variables-wind-names.css" server="C:/xampp/htdocs/icems/" local="131648441832908163" remote="131648441830000000" Dst="0" />
<file name="variables-beaufort.css" server="C:/xampp/htdocs/icems/" local="131648441835129748" remote="131648441830000000" Dst="0" />
<file name="variables-day.css" server="C:/xampp/htdocs/icems/" local="131648441840183332" remote="131648441840000000" Dst="0" />
<file name="variables-misc.css" server="C:/xampp/htdocs/icems/" local="131648441847018194" remote="131648441840000000" Dst="0" />
<file name="variables-neutral.css" server="C:/xampp/htdocs/icems/" local="131648441848088953" remote="131648441840000000" Dst="0" />
</dwsync>